webcomix/__init__.py
webcomix/cli.py
webcomix/comic.py
webcomix/docker.py
webcomix/exceptions.py
webcomix/scrapy/__init__.py
webcomix/scrapy/crawler_worker.py
webcomix/scrapy/custom_cloudflare_middleware.py
webcomix/scrapy/download/__init__.py
webcomix/scrapy/download/comic_page.py
webcomix/scrapy/download/comic_pipeline.py
webcomix/scrapy/download/comic_spider.py
webcomix/scrapy/download/tests/__init__.py
webcomix/scrapy/download/tests/test_comic_pipeline.py
webcomix/scrapy/download/tests/test_comic_spider.py
webcomix/scrapy/request_factory.py
webcomix/scrapy/tests/__init__.py
webcomix/scrapy/tests/test_crawler_worker.py
webcomix/scrapy/tests/test_custom_cloudflare_middleware.py
webcomix/scrapy/tests/test_request_factory.py
webcomix/scrapy/util.py
webcomix/scrapy/verification/__init__.py
webcomix/scrapy/verification/verification_spider.py
webcomix/scrapy/verification/web_page.py
webcomix/search.py
webcomix/supported_comics.py
webcomix/tests/__init__.py
webcomix/tests/fake_websites/fixture.py
webcomix/tests/fake_websites/one_webpage/1.html
webcomix/tests/fake_websites/one_webpage/1.jpeg
webcomix/tests/fake_websites/one_webpage/2.jpeg
webcomix/tests/fake_websites/one_webpage_searchable/1.html
webcomix/tests/fake_websites/one_webpage_searchable/1.jpeg
webcomix/tests/fake_websites/one_webpage_searchable/2.jpeg
webcomix/tests/fake_websites/three_webpages/1.html
webcomix/tests/fake_websites/three_webpages/1.jpeg
webcomix/tests/fake_websites/three_webpages/2.html
webcomix/tests/fake_websites/three_webpages/2.jpeg
webcomix/tests/fake_websites/three_webpages/3.html
webcomix/tests/fake_websites/three_webpages_alt_text/1.html
webcomix/tests/fake_websites/three_webpages_alt_text/1.jpeg
webcomix/tests/fake_websites/three_webpages_alt_text/2.html
webcomix/tests/fake_websites/three_webpages_alt_text/2.jpeg
webcomix/tests/fake_websites/three_webpages_alt_text/3.html
webcomix/tests/fake_websites/three_webpages_classes/1.html
webcomix-3.12.0.dist-info/METADATA
webcomix-3.12.0.dist-info/WHEEL
webcomix-3.12.0.dist-info/entry_points.txt
webcomix-3.12.0.dist-info/licenses/LICENSE
webcomix-3.12.0.dist-info/RECORD
