Metadata-Version: 2.4
Name: webcomix
Version: 3.12.0
Summary: Webcomic downloader
License: MIT
License-File: LICENSE
Author: Jean-Christophe Pelletier
Author-email: pelletierj97@gmail.com
Requires-Python: >=3.9,<4.0
Classifier: Development Status :: 5 - Production/Stable
Classifier: Framework :: Scrapy
Classifier: Intended Audience :: End Users/Desktop
Classifier: License :: OSI Approved :: MIT License
Classifier: Operating System :: OS Independent
Classifier: Programming Language :: Python
Classifier: Programming Language :: Python :: 3
Classifier: Programming Language :: Python :: 3.9
Classifier: Programming Language :: Python :: 3.10
Classifier: Programming Language :: Python :: 3.11
Classifier: Programming Language :: Python :: 3.12
Classifier: Programming Language :: Python :: 3.13
Classifier: Programming Language :: Python :: 3.14
Classifier: Programming Language :: Python :: 3.8
Classifier: Topic :: Internet :: WWW/HTTP
Requires-Dist: Scrapy (>=2.11.2,<3.0.0)
Requires-Dist: click (>=8.0.0,<9.0.0)
Requires-Dist: cloudscraper (>=1.2.71,<2.0.0)
Requires-Dist: docker (>=7.1.0,<8.0.0)
Requires-Dist: pytest-rerunfailures (>=11.1.2,<12.0.0)
Requires-Dist: scrapy-fake-useragent (>=1.4.4,<2.0.0)
Requires-Dist: scrapy-splash (>=0.10.0,<0.11.0)
Requires-Dist: tqdm (>=4.66.1,<5.0.0)
Project-URL: Homepage, https://github.com/J-CPelletier/webcomix
Project-URL: Repository, https://github.com/J-CPelletier/webcomix
